sms4/__init__.py
sms4/sms4.py
sms4-0.1.0.dist-info/LICENSE
sms4-0.1.0.dist-info/METADATA
sms4-0.1.0.dist-info/WHEEL
sms4-0.1.0.dist-info/top_level.txt
sms4-0.1.0.dist-info/RECORD
