Metadata-Version: 2.1
Name: sms4
Version: 0.1.0
Summary: Simple and straightforward way to send text messages
Home-page: https://sms4.dev
Author: Sergey Gaykov
Author-email: sdgaykov@gmail.com
License: MIT
Platform: UNKNOWN
Classifier: Development Status :: 3 - Alpha
Classifier: License :: OSI Approved :: MIT License
Classifier: Intended Audience :: Developers
Classifier: Topic :: Communications :: Telephony
Classifier: Topic :: Software Development :: Libraries :: Python Modules
Classifier: Programming Language :: Python :: 2
Classifier: Programming Language :: Python :: 2.7
Requires-Dist: requests
